{
  "annotations": {
    "changelogDate": "20250520212322"
  },
  "applications": ["gateway", "reportingService"],
  "clientRootFolder": "reportingService",
  "databaseType": "sql",
  "dto": "mapstruct",
  "fields": [
    {
      "fieldName": "nom",
      "fieldType": "String",
      "fieldValidateRules": ["required"]
    },
    {
      "fieldName": "valeur",
      "fieldType": "Float",
      "fieldValidateRules": ["required"]
    }
  ],
  "microserviceName": "reportingService",
  "name": "Indicateur",
  "pagination": "pagination",
  "relationships": [],
  "searchEngine": "elasticsearch",
  "service": "serviceImpl"
}
