{
  "annotations": {
    "changelogDate": "20250520210722"
  },
  "applications": ["gateway", "curriculumService"],
  "clientRootFolder": "curriculumService",
  "databaseType": "sql",
  "dto": "mapstruct",
  "fields": [
    {
      "fieldName": "intitule",
      "fieldType": "String",
      "fieldValidateRules": ["required"]
    },
    {
      "fieldName": "codeProgramme",
      "fieldType": "String",
      "fieldValidateRules": ["required", "unique"]
    }
  ],
  "microserviceName": "curriculumService",
  "name": "Programme",
  "pagination": "pagination",
  "relationships": [],
  "searchEngine": "no",
  "service": "serviceImpl"
}
